llm_text_splitter/__init__.py
llm_text_splitter/readers.py
llm_text_splitter/splitter.py
llm_text_splitter-0.2.0.dist-info/licenses/LICENSE
llm_text_splitter-0.2.0.dist-info/METADATA
llm_text_splitter-0.2.0.dist-info/WHEEL
llm_text_splitter-0.2.0.dist-info/top_level.txt
llm_text_splitter-0.2.0.dist-info/RECORD
