Metadata-Version: 2.4
Name: llm-text-splitter
Version: 0.2.0
Summary: A lightweight, rule-based text splitter for LLM context window management, handles multiple file formats and enriches chunks with metadata.
Author-email: Mohamed Elghobary <m.abdeltawab.elghobary@gmail.com>
Project-URL: Homepage, https://github.com/MohamedElghobary/llm_text_splitter
Project-URL: Bug Tracker, https://github.com/MohamedElghobary/llm_text_splitter/issues
Project-URL: Source Code, https://github.com/MohamedElghobary/llm_text_splitter
Keywords: LLM,text-splitter,chunking,RAG,document-processing
Classifier: Development Status :: 4 - Beta
Classifier: Programming Language :: Python :: 3
Classifier: Programming Language :: Python :: 3.10
Classifier: Programming Language :: Python :: 3.11
Classifier: Programming Language :: Python :: 3.12
Classifier: License :: OSI Approved :: MIT License
Classifier: Operating System :: OS Independent
Classifier: Topic :: Text Processing
Classifier: Topic :: Text Processing :: General
Classifier: Topic :: Scientific/Engineering :: Artificial Intelligence
Classifier: Intended Audience :: Developers
Requires-Python: >=3.12
License-File: LICENSE
Requires-Dist: pypdf>=3.0.0
Requires-Dist: python-docx>=0.8.0
Requires-Dist: beautifulsoup4>=4.0.0
Provides-Extra: dev
Requires-Dist: pytest>=7.0; extra == "dev"
Requires-Dist: pytest-cov; extra == "dev"
Dynamic: license-file
